tests/__init__.py
tests/test_storage_clients.py
vishwa_fastapi_utils-0.0.29.dist-info/licenses/LICENSE
vishwa_labs_fastapi_utils/__init__.py
vishwa_labs_fastapi_utils/cloud/__init__.py
vishwa_labs_fastapi_utils/cloud/az_blob.py
vishwa_labs_fastapi_utils/cloud/az_blob_async.py
vishwa_labs_fastapi_utils/cloud/gcs.py
vishwa_labs_fastapi_utils/cloud/gcs_async.py
vishwa_labs_fastapi_utils/cloud/storage.py
vishwa_labs_fastapi_utils/cloud/storage_base.py
vishwa_labs_fastapi_utils/cloud/utils.py
vishwa_labs_fastapi_utils/constants/__init__.py
vishwa_labs_fastapi_utils/core/__init__.py
vishwa_labs_fastapi_utils/core/common.py
vishwa_labs_fastapi_utils/logging/__init__.py
vishwa_labs_fastapi_utils/logging/fastapi_log_config.py
vishwa_labs_fastapi_utils/logging/setup_logger.py
vishwa_labs_fastapi_utils/metrics_handler/__init__.py
vishwa_labs_fastapi_utils/metrics_handler/prometheus.py
vishwa_labs_fastapi_utils/server/__init__.py
vishwa_labs_fastapi_utils/server/common.py
vishwa_labs_fastapi_utils/server/route_handlers/__init__.py
vishwa_labs_fastapi_utils/server/route_handlers/telemetry.py
vishwa_labs_fastapi_utils/telemetry/__init__.py
vishwa_labs_fastapi_utils/telemetry/otel.py
vishwa_labs_fastapi_utils/utils/__init__.py
vishwa_fastapi_utils-0.0.29.dist-info/METADATA
vishwa_fastapi_utils-0.0.29.dist-info/WHEEL
vishwa_fastapi_utils-0.0.29.dist-info/top_level.txt
vishwa_fastapi_utils-0.0.29.dist-info/RECORD
